MANIFEST.in
README.rst
requirements.txt
setup.py
aiodcard/__init__.py
aiodcard/aiodcard.py
aiodcard.egg-info/PKG-INFO
aiodcard.egg-info/SOURCES.txt
aiodcard.egg-info/dependency_links.txt
aiodcard.egg-info/top_level.txt
tests/__init__.py
tests/test_aiodcard.py