Metadata-Version: 1.1
Name: aiodcard
Version: 0.1.0
Summary: Dcard crawler using asyncio(coroutine)
Home-page: https://github.com/carlcarl/aiodcard
Author: carlcarl
Author-email: carlcarlking@gmail.com
License: MIT
Keywords: dcard,crawler,coroutine
Platform: UNKNOWN
Classifier: Development Status :: 4 - Beta
Classifier: Environment :: Console
Classifier: Intended Audience :: Developers
Classifier: License :: OSI Approved :: MIT License
Classifier: Operating System :: MacOS :: MacOS X
Classifier: Operating System :: POSIX
Classifier: Operating System :: Unix
Classifier: Programming Language :: Python :: 3 :: Only
Classifier: Topic :: Software Development :: Libraries
